secure_password_manager/__init__.py
secure_password_manager/apps/__init__.py
secure_password_manager/apps/app.py
secure_password_manager/apps/gui.py
secure_password_manager/services/browser_bridge.py
secure_password_manager/utils/__init__.py
secure_password_manager/utils/auth.py
secure_password_manager/utils/backup.py
secure_password_manager/utils/config.py
secure_password_manager/utils/crypto.py
secure_password_manager/utils/database.py
secure_password_manager/utils/interactive.py
secure_password_manager/utils/key_management.py
secure_password_manager/utils/logger.py
secure_password_manager/utils/password_analysis.py
secure_password_manager/utils/paths.py
secure_password_manager/utils/security_analyzer.py
secure_password_manager/utils/security_audit.py
secure_password_manager/utils/two_factor.py
secure_password_manager/utils/ui.py
secure_password_manager-1.8.4.dist-info/METADATA
secure_password_manager-1.8.4.dist-info/WHEEL
secure_password_manager-1.8.4.dist-info/entry_points.txt
secure_password_manager-1.8.4.dist-info/top_level.txt
secure_password_manager-1.8.4.dist-info/RECORD
