Metadata-Version: 2.4
Name: secure-password-manager
Version: 1.8.4
Summary: A secure local password manager with strong encryption
Author-email: ArcheWizard <faress22.dadi@gmail.com>
License: MIT
Project-URL: Homepage, https://github.com/ArcheWizard/Password_Manager
Project-URL: Documentation, https://github.com/ArcheWizard/Password_Manager/tree/main/docs
Project-URL: Repository, https://github.com/ArcheWizard/Password_Manager
Project-URL: Issues, https://github.com/ArcheWizard/Password_Manager/issues
Project-URL: Changelog, https://github.com/ArcheWizard/Password_Manager/blob/main/CHANGELOG.md
Keywords: password,manager,security,encryption,2fa
Classifier: Programming Language :: Python :: 3
Classifier: Programming Language :: Python :: 3.8
Classifier: Programming Language :: Python :: 3.9
Classifier: Programming Language :: Python :: 3.10
Classifier: Programming Language :: Python :: 3.11
Classifier: Programming Language :: Python :: 3.12
Classifier: Operating System :: OS Independent
Classifier: Development Status :: 4 - Beta
Classifier: Topic :: Security
Classifier: Topic :: Utilities
Classifier: License :: OSI Approved :: MIT License
Requires-Python: >=3.8
Requires-Dist: cryptography>=41.0.0
Requires-Dist: PyQt5>=5.15.9
Requires-Dist: pillow>=10.0.0
Requires-Dist: zxcvbn>=4.4.28
Requires-Dist: colorama>=0.4.6
Requires-Dist: pyperclip>=1.8.2
Requires-Dist: requests>=2.28.1
Requires-Dist: pyotp>=2.8.0
Requires-Dist: qrcode>=7.4.2
Requires-Dist: typing-extensions>=4.7.1
Requires-Dist: fastapi>=0.114.0
Requires-Dist: uvicorn[standard]>=0.30.5
Requires-Dist: pydantic>=2.7.0
Provides-Extra: dev
Requires-Dist: pytest>=7.0.0; extra == "dev"
Requires-Dist: pytest-cov>=4.0.0; extra == "dev"
Requires-Dist: black>=23.0.0; extra == "dev"
Requires-Dist: ruff>=0.1.0; extra == "dev"
